iam_client/__init__.py
iam_client/client.py
iam_client/exceptions.py
iam_client/schemas.py
iam_client-0.1.7.dist-info/METADATA
iam_client-0.1.7.dist-info/WHEEL
iam_client-0.1.7.dist-info/top_level.txt
iam_client-0.1.7.dist-info/RECORD
