Metadata-Version: 2.4
Name: iam-client
Version: 0.1.7
Summary: IAM client for services
Requires-Python: >=3.10
Requires-Dist: httpx>=0.25.0
Requires-Dist: pydantic>=2.5.0
